kepost/__init__.py
kepost/atlases/__init__.py
kepost/atlases/available_atlases/__init__.py
kepost/atlases/available_atlases/available_atlases.py
kepost/atlases/available_atlases/fan2016/MNI152/space-MNI152_atlas-fan2016_res-1mm_dseg.csv
kepost/atlases/available_atlases/fan2016/MNI152/space-MNI152_atlas-fan2016_res-1mm_dseg.nii.gz
kepost/atlases/available_atlases/fan2016/MNI152/space-MNI152_atlas-fan2016_res-1mm_dseg.tsv
kepost/atlases/available_atlases/fan2016/fsaverage/desc-lut_space-fsaverage_atlas-fan2016.txt
kepost/atlases/available_atlases/fan2016/fsaverage/fsaverage_164k/hemi-L_space-fsaverage_atlas-fan2016_den-164k.label.gii
kepost/atlases/available_atlases/fan2016/fsaverage/fsaverage_164k/hemi-R_space-fsaverage_atlas-fan2016_den-164k.label.gii
kepost/atlases/available_atlases/fan2016/fsaverage/fsaverage_164k/space-fsaverage_atlas-fan2016_den-164k.dlabel.nii
kepost/atlases/available_atlases/fan2016/fsaverage/fsaverage_32k/hemi-L_space-fsaverage_atlas-fan2016_den-32k.label.gii
kepost/atlases/available_atlases/fan2016/fsaverage/fsaverage_32k/hemi-R_space-fsaverage_atlas-fan2016_den-32k.label.gii
kepost/atlases/available_atlases/fan2016/fsaverage/fsaverage_32k/space-fsaverage_atlas-fan2016_den-32k.dlabel.nii
kepost/atlases/available_atlases/fan2016/fsaverage/hemi-L_space-fsaverage_atlas-fan2016.gcs
kepost/atlases/available_atlases/fan2016/fsaverage/hemi-R_space-fsaverage_atlas-fan2016.gcs
kepost/atlases/available_atlases/fan2016/fsaverage/hemi-subcortex_space-fsaverage_atlas-fan2016.gca
kepost/atlases/available_atlases/fan2016/references.bib
kepost/atlases/available_atlases/huang2022/MNI152/space-MNI152_atlas-huang2022_res-1mm_dseg.csv
kepost/atlases/available_atlases/huang2022/MNI152/space-MNI152_atlas-huang2022_res-1mm_dseg.nii.gz
kepost/atlases/available_atlases/huang2022/MNI152/space-MNI152_atlas-huang2022_res-1mm_dseg.tsv
kepost/atlases/available_atlases/huang2022/references.bib
kepost-0.2.25.dist-info/AUTHORS.rst
kepost-0.2.25.dist-info/LICENSE
kepost-0.2.25.dist-info/METADATA
kepost-0.2.25.dist-info/WHEEL
kepost-0.2.25.dist-info/RECORD
