Metadata-Version: 2.3
Name: kepost
Version: 0.2.25
Summary: Post-processing for dMRI derivatives of the Strauss Neuroplasticity Brain Bank (SNBB)
License: MIT
Author: Gal Kepler
Author-email: galkepler@gmail.com
Maintainer: Gal Kepler
Maintainer-email: galkepler@gmail.com
Requires-Python: >=3.10,<4.0
Classifier: Development Status :: 2 - Pre-Alpha
Classifier: Intended Audience :: Science/Research
Classifier: License :: OSI Approved :: MIT License
Classifier: Programming Language :: Python :: 3
Classifier: Programming Language :: Python :: 3.10
Classifier: Programming Language :: Python :: 3.11
Classifier: Programming Language :: Python :: 3.12
Classifier: Programming Language :: Python :: 3.13
Classifier: Programming Language :: Python :: 3.8
Classifier: Programming Language :: Python :: 3.9
Requires-Dist: acres (>=0.1.0,<0.2.0)
Requires-Dist: cvxpy (>=1.5.2,<2.0.0)
Requires-Dist: dipy (>=1.9.0,<2.0.0)
Requires-Dist: doc8 (>=1.1.1,<2.0.0)
Requires-Dist: fury (>=0.10.0,<0.11.0)
Requires-Dist: mne-connectivity (>=0.7.0,<0.8.0)
Requires-Dist: neuromaps (>=0.0.5,<0.0.6)
Requires-Dist: nipype (>=1.9.0,<2.0.0)
Requires-Dist: nireports (>=23.2.1,<24.0.0)
Requires-Dist: niworkflows (>=1.8.1,<2.0.0)
Requires-Dist: numpy (>=1.26.0,<2.0.0)
Requires-Dist: pre-commit (>=3.3.3,<4.0.0)
Requires-Dist: psutil (>=5.9.5,<6.0.0)
Requires-Dist: pytest-cov (>=5.0.0,<6.0.0)
Requires-Dist: pyupgrade (>=3.9.0,<4.0.0)
Requires-Dist: sdcflows (>=2.5.1,<3.0.0)
Requires-Dist: smriprep (>=0.12.1,<0.13.0)
Requires-Dist: templateflow (>=23.0.0,<24.0.0)
Requires-Dist: toml (>=0.10.2,<0.11.0)
Requires-Dist: tox (>=4.16.0,<5.0.0)
Project-URL: Homepage, https://github.com//GalKepler/kepost
Project-URL: bugs, https://github.com/GalKepler/kepost/issues
Project-URL: changelog, https://github.com//GalKepler/kepost/blob/master/changelog.md
